{"cameraMode":{"drawMode":0,"name":"Shaded","section":"Shading Mode"},"sceneLighting":false,"audioPlay":false,"sceneViewState":{"m_AlwaysRefresh":false,"showFog":true,"showSkybox":false,"showFlares":true,"showImageEffects":true,"showParticleSystems":true,"showVisualEffectGraphs":true,"m_FxEnabled":true},"in2DMode":false,"pivot":{"x":-79.0462875366211,"y":9.113784790039063,"z":-49.618587493896487},"rotation":{"x":0.17989225685596467,"y":0.5040730834007263,"z":-0.08479827642440796,"w":0.843055248260498},"size":7.020448684692383,"orthographic":false}